{"match_id": "1f734ef0-0965-4a05-9b3e-c7ef5ef52e31.nakama-0", "map_id": "AmbroseValley", "positions": [{"user_id": "648579b2-2bf5-43ef-9bb1-ef0a0c06c302", "is_human": true, "px": 61.7, "py": 481.1, "t": 0.0, "event": "Position"}, {"user_id": "648579b2-2bf5-43ef-9bb1-ef0a0c06c302", "is_human": true, "px": 74.8, "py": 459.5, "t": 0.0, "event": "Position"}, {"user_id": "648579b2-2bf5-43ef-9bb1-ef0a0c06c302", "is_human": true, "px": 67.6, "py": 433.5, "t": 0.0, "event": "Position"}, {"user_id": "648579b2-2bf5-43ef-9bb1-ef0a0c06c302", "is_human": true, "px": 72.8, "py": 408.6, "t": 0.0, "event": "Position"}, {"user_id": "648579b2-2bf5-43ef-9bb1-ef0a0c06c302", "is_human": true, "px": 82.2, "py": 386.5, "t": 0.0, "event": "Position"}, {"user_id": "648579b2-2bf5-43ef-9bb1-ef0a0c06c302", "is_human": true, "px": 84.8, "py": 399.7, "t": 0.0, "event": "Position"}, {"user_id": "648579b2-2bf5-43ef-9bb1-ef0a0c06c302", "is_human": true, "px": 96.1, "py": 407.7, "t": 0.0, "event": "Position"}, {"user_id": "648579b2-2bf5-43ef-9bb1-ef0a0c06c302", "is_human": true, "px": 106.4, "py": 404.0, "t": 0.0, "event": "Position"}, {"user_id": "648579b2-2bf5-43ef-9bb1-ef0a0c06c302", "is_human": true, "px": 104.5, "py": 409.1, "t": 0.0, "event": "Position"}, {"user_id": "648579b2-2bf5-43ef-9bb1-ef0a0c06c302", "is_human": true, "px": 99.1, "py": 415.5, "t": 0.1, "event": "Position"}, {"user_id": "648579b2-2bf5-43ef-9bb1-ef0a0c06c302", "is_human": true, "px": 96.1, "py": 409.9, "t": 0.1, "event": "Position"}, {"user_id": "648579b2-2bf5-43ef-9bb1-ef0a0c06c302", "is_human": true, "px": 117.6, "py": 409.8, "t": 0.1, "event": "Position"}, {"user_id": "648579b2-2bf5-43ef-9bb1-ef0a0c06c302", "is_human": true, "px": 131.7, "py": 395.7, "t": 0.1, "event": "Position"}, {"user_id": "648579b2-2bf5-43ef-9bb1-ef0a0c06c302", "is_human": true, "px": 136.9, "py": 397.4, "t": 0.1, "event": "Position"}, {"user_id": "648579b2-2bf5-43ef-9bb1-ef0a0c06c302", "is_human": true, "px": 148.1, "py": 398.4, "t": 0.1, "event": "Position"}, {"user_id": "648579b2-2bf5-43ef-9bb1-ef0a0c06c302", "is_human": true, "px": 165.2, "py": 405.2, "t": 0.1, "event": "Position"}, {"user_id": "648579b2-2bf5-43ef-9bb1-ef0a0c06c302", "is_human": true, "px": 200.0, "py": 414.8, "t": 0.1, "event": "Position"}, {"user_id": "648579b2-2bf5-43ef-9bb1-ef0a0c06c302", "is_human": true, "px": 219.3, "py": 421.1, "t": 0.1, "event": "Position"}, {"user_id": "648579b2-2bf5-43ef-9bb1-ef0a0c06c302", "is_human": true, "px": 227.6, "py": 423.3, "t": 0.1, "event": "Position"}, {"user_id": "648579b2-2bf5-43ef-9bb1-ef0a0c06c302", "is_human": true, "px": 227.6, "py": 423.0, "t": 0.1, "event": "Position"}, {"user_id": "648579b2-2bf5-43ef-9bb1-ef0a0c06c302", "is_human": true, "px": 235.6, "py": 417.1, "t": 0.1, "event": "Position"}, {"user_id": "648579b2-2bf5-43ef-9bb1-ef0a0c06c302", "is_human": true, "px": 244.4, "py": 417.5, "t": 0.1, "event": "Position"}, {"user_id": "648579b2-2bf5-43ef-9bb1-ef0a0c06c302", "is_human": true, "px": 267.1, "py": 415.3, "t": 0.1, "event": "Position"}, {"user_id": "648579b2-2bf5-43ef-9bb1-ef0a0c06c302", "is_human": true, "px": 279.3, "py": 429.4, "t": 0.1, "event": "Position"}, {"user_id": "648579b2-2bf5-43ef-9bb1-ef0a0c06c302", "is_human": true, "px": 278.0, "py": 432.5, "t": 0.1, "event": "Position"}, {"user_id": "648579b2-2bf5-43ef-9bb1-ef0a0c06c302", "is_human": true, "px": 279.7, "py": 432.5, "t": 0.2, "event": "Position"}, {"user_id": "648579b2-2bf5-43ef-9bb1-ef0a0c06c302", "is_human": true, "px": 278.3, "py": 432.8, "t": 0.2, "event": "Position"}], "combat": [{"user_id": "648579b2-2bf5-43ef-9bb1-ef0a0c06c302", "is_human": true, "px": 106.4, "py": 404.0, "t": 0.0, "event": "Loot"}, {"user_id": "648579b2-2bf5-43ef-9bb1-ef0a0c06c302", "is_human": true, "px": 104.5, "py": 409.1, "t": 0.1, "event": "Loot"}, {"user_id": "648579b2-2bf5-43ef-9bb1-ef0a0c06c302", "is_human": true, "px": 279.3, "py": 429.4, "t": 0.1, "event": "Loot"}, {"user_id": "648579b2-2bf5-43ef-9bb1-ef0a0c06c302", "is_human": true, "px": 278.3, "py": 432.8, "t": 0.2, "event": "BotKilled"}]}