{"match_id": "29ed797b-66b6-44e4-abc2-e98b9732fbd6.nakama-0", "map_id": "AmbroseValley", "positions": [{"user_id": "484d027b-069e-4b38-b99a-54f3bbfedc7e", "is_human": true, "px": 299.1, "py": 898.5, "t": 0.0, "event": "Position"}, {"user_id": "484d027b-069e-4b38-b99a-54f3bbfedc7e", "is_human": true, "px": 304.1, "py": 894.2, "t": 0.0, "event": "Position"}, {"user_id": "484d027b-069e-4b38-b99a-54f3bbfedc7e", "is_human": true, "px": 302.3, "py": 899.9, "t": 0.0, "event": "Position"}, {"user_id": "484d027b-069e-4b38-b99a-54f3bbfedc7e", "is_human": true, "px": 336.7, "py": 892.0, "t": 0.0, "event": "Position"}, {"user_id": "484d027b-069e-4b38-b99a-54f3bbfedc7e", "is_human": true, "px": 353.0, "py": 892.2, "t": 0.0, "event": "Position"}, {"user_id": "484d027b-069e-4b38-b99a-54f3bbfedc7e", "is_human": true, "px": 360.5, "py": 893.9, "t": 0.0, "event": "Position"}, {"user_id": "484d027b-069e-4b38-b99a-54f3bbfedc7e", "is_human": true, "px": 361.3, "py": 888.2, "t": 0.1, "event": "Position"}, {"user_id": "484d027b-069e-4b38-b99a-54f3bbfedc7e", "is_human": true, "px": 354.8, "py": 883.3, "t": 0.1, "event": "Position"}, {"user_id": "484d027b-069e-4b38-b99a-54f3bbfedc7e", "is_human": true, "px": 362.8, "py": 887.2, "t": 0.1, "event": "Position"}, {"user_id": "484d027b-069e-4b38-b99a-54f3bbfedc7e", "is_human": true, "px": 373.9, "py": 894.6, "t": 0.1, "event": "Position"}, {"user_id": "484d027b-069e-4b38-b99a-54f3bbfedc7e", "is_human": true, "px": 370.9, "py": 888.9, "t": 0.1, "event": "Position"}, {"user_id": "484d027b-069e-4b38-b99a-54f3bbfedc7e", "is_human": true, "px": 371.3, "py": 892.0, "t": 0.1, "event": "Position"}, {"user_id": "484d027b-069e-4b38-b99a-54f3bbfedc7e", "is_human": true, "px": 377.8, "py": 890.0, "t": 0.1, "event": "Position"}, {"user_id": "484d027b-069e-4b38-b99a-54f3bbfedc7e", "is_human": true, "px": 365.5, "py": 904.0, "t": 0.1, "event": "Position"}, {"user_id": "484d027b-069e-4b38-b99a-54f3bbfedc7e", "is_human": true, "px": 382.7, "py": 908.8, "t": 0.1, "event": "Position"}, {"user_id": "484d027b-069e-4b38-b99a-54f3bbfedc7e", "is_human": true, "px": 382.0, "py": 903.6, "t": 0.2, "event": "Position"}, {"user_id": "484d027b-069e-4b38-b99a-54f3bbfedc7e", "is_human": true, "px": 375.6, "py": 873.3, "t": 0.2, "event": "Position"}, {"user_id": "484d027b-069e-4b38-b99a-54f3bbfedc7e", "is_human": true, "px": 407.4, "py": 855.0, "t": 0.2, "event": "Position"}, {"user_id": "484d027b-069e-4b38-b99a-54f3bbfedc7e", "is_human": true, "px": 426.3, "py": 842.8, "t": 0.2, "event": "Position"}, {"user_id": "484d027b-069e-4b38-b99a-54f3bbfedc7e", "is_human": true, "px": 423.8, "py": 823.1, "t": 0.2, "event": "Position"}, {"user_id": "484d027b-069e-4b38-b99a-54f3bbfedc7e", "is_human": true, "px": 417.4, "py": 804.2, "t": 0.2, "event": "Position"}, {"user_id": "484d027b-069e-4b38-b99a-54f3bbfedc7e", "is_human": true, "px": 418.3, "py": 807.7, "t": 0.2, "event": "Position"}, {"user_id": "484d027b-069e-4b38-b99a-54f3bbfedc7e", "is_human": true, "px": 401.4, "py": 806.9, "t": 0.2, "event": "Position"}, {"user_id": "484d027b-069e-4b38-b99a-54f3bbfedc7e", "is_human": true, "px": 415.7, "py": 803.5, "t": 0.2, "event": "Position"}, {"user_id": "484d027b-069e-4b38-b99a-54f3bbfedc7e", "is_human": true, "px": 410.5, "py": 801.2, "t": 0.2, "event": "Position"}, {"user_id": "484d027b-069e-4b38-b99a-54f3bbfedc7e", "is_human": true, "px": 408.2, "py": 797.5, "t": 0.2, "event": "Position"}, {"user_id": "484d027b-069e-4b38-b99a-54f3bbfedc7e", "is_human": true, "px": 406.0, "py": 807.2, "t": 0.2, "event": "Position"}, {"user_id": "484d027b-069e-4b38-b99a-54f3bbfedc7e", "is_human": true, "px": 401.1, "py": 806.0, "t": 0.2, "event": "Position"}, {"user_id": "484d027b-069e-4b38-b99a-54f3bbfedc7e", "is_human": true, "px": 405.0, "py": 801.9, "t": 0.2, "event": "Position"}, {"user_id": "484d027b-069e-4b38-b99a-54f3bbfedc7e", "is_human": true, "px": 406.2, "py": 805.2, "t": 0.2, "event": "Position"}, {"user_id": "484d027b-069e-4b38-b99a-54f3bbfedc7e", "is_human": true, "px": 410.2, "py": 807.0, "t": 0.2, "event": "Position"}, {"user_id": "484d027b-069e-4b38-b99a-54f3bbfedc7e", "is_human": true, "px": 416.1, "py": 810.4, "t": 0.3, "event": "Position"}, {"user_id": "484d027b-069e-4b38-b99a-54f3bbfedc7e", "is_human": true, "px": 411.8, "py": 803.0, "t": 0.3, "event": "Position"}, {"user_id": "484d027b-069e-4b38-b99a-54f3bbfedc7e", "is_human": true, "px": 417.0, "py": 799.2, "t": 0.3, "event": "Position"}, {"user_id": "484d027b-069e-4b38-b99a-54f3bbfedc7e", "is_human": true, "px": 414.4, "py": 799.5, "t": 0.3, "event": "Position"}, {"user_id": "484d027b-069e-4b38-b99a-54f3bbfedc7e", "is_human": true, "px": 418.0, "py": 800.6, "t": 0.3, "event": "Position"}, {"user_id": "484d027b-069e-4b38-b99a-54f3bbfedc7e", "is_human": true, "px": 409.8, "py": 798.4, "t": 0.3, "event": "Position"}, {"user_id": "484d027b-069e-4b38-b99a-54f3bbfedc7e", "is_human": true, "px": 408.9, "py": 793.4, "t": 0.3, "event": "Position"}, {"user_id": "484d027b-069e-4b38-b99a-54f3bbfedc7e", "is_human": true, "px": 403.2, "py": 782.5, "t": 0.3, "event": "Position"}, {"user_id": "484d027b-069e-4b38-b99a-54f3bbfedc7e", "is_human": true, "px": 426.6, "py": 756.4, "t": 0.3, "event": "Position"}, {"user_id": "484d027b-069e-4b38-b99a-54f3bbfedc7e", "is_human": true, "px": 445.2, "py": 722.3, "t": 0.3, "event": "Position"}, {"user_id": "484d027b-069e-4b38-b99a-54f3bbfedc7e", "is_human": true, "px": 450.5, "py": 710.4, "t": 0.3, "event": "Position"}, {"user_id": "484d027b-069e-4b38-b99a-54f3bbfedc7e", "is_human": true, "px": 456.5, "py": 701.8, "t": 0.3, "event": "Position"}, {"user_id": "484d027b-069e-4b38-b99a-54f3bbfedc7e", "is_human": true, "px": 468.7, "py": 707.2, "t": 0.3, "event": "Position"}, {"user_id": "484d027b-069e-4b38-b99a-54f3bbfedc7e", "is_human": true, "px": 474.4, "py": 724.0, "t": 0.3, "event": "Position"}, {"user_id": "484d027b-069e-4b38-b99a-54f3bbfedc7e", "is_human": true, "px": 484.5, "py": 735.8, "t": 0.3, "event": "Position"}, {"user_id": "484d027b-069e-4b38-b99a-54f3bbfedc7e", "is_human": true, "px": 498.3, "py": 732.9, "t": 0.3, "event": "Position"}, {"user_id": "484d027b-069e-4b38-b99a-54f3bbfedc7e", "is_human": true, "px": 513.3, "py": 738.2, "t": 0.3, "event": "Position"}, {"user_id": "484d027b-069e-4b38-b99a-54f3bbfedc7e", "is_human": true, "px": 527.9, "py": 766.7, "t": 0.3, "event": "Position"}, {"user_id": "484d027b-069e-4b38-b99a-54f3bbfedc7e", "is_human": true, "px": 539.2, "py": 765.9, "t": 0.3, "event": "Position"}, {"user_id": "484d027b-069e-4b38-b99a-54f3bbfedc7e", "is_human": true, "px": 548.1, "py": 769.2, "t": 0.3, "event": "Position"}, {"user_id": "484d027b-069e-4b38-b99a-54f3bbfedc7e", "is_human": true, "px": 535.2, "py": 768.5, "t": 0.4, "event": "Position"}, {"user_id": "484d027b-069e-4b38-b99a-54f3bbfedc7e", "is_human": true, "px": 531.4, "py": 777.8, "t": 0.4, "event": "Position"}, {"user_id": "484d027b-069e-4b38-b99a-54f3bbfedc7e", "is_human": true, "px": 529.0, "py": 776.9, "t": 0.4, "event": "Position"}, {"user_id": "484d027b-069e-4b38-b99a-54f3bbfedc7e", "is_human": true, "px": 532.5, "py": 779.1, "t": 0.4, "event": "Position"}, {"user_id": "484d027b-069e-4b38-b99a-54f3bbfedc7e", "is_human": true, "px": 534.0, "py": 782.4, "t": 0.4, "event": "Position"}, {"user_id": "484d027b-069e-4b38-b99a-54f3bbfedc7e", "is_human": true, "px": 522.9, "py": 786.3, "t": 0.4, "event": "Position"}, {"user_id": "484d027b-069e-4b38-b99a-54f3bbfedc7e", "is_human": true, "px": 532.8, "py": 785.1, "t": 0.4, "event": "Position"}, {"user_id": "484d027b-069e-4b38-b99a-54f3bbfedc7e", "is_human": true, "px": 535.8, "py": 783.7, "t": 0.4, "event": "Position"}, {"user_id": "484d027b-069e-4b38-b99a-54f3bbfedc7e", "is_human": true, "px": 533.0, "py": 782.5, "t": 0.4, "event": "Position"}, {"user_id": "484d027b-069e-4b38-b99a-54f3bbfedc7e", "is_human": true, "px": 537.4, "py": 784.0, "t": 0.4, "event": "Position"}, {"user_id": "484d027b-069e-4b38-b99a-54f3bbfedc7e", "is_human": true, "px": 551.3, "py": 794.1, "t": 0.4, "event": "Position"}, {"user_id": "484d027b-069e-4b38-b99a-54f3bbfedc7e", "is_human": true, "px": 555.8, "py": 807.0, "t": 0.4, "event": "Position"}, {"user_id": "484d027b-069e-4b38-b99a-54f3bbfedc7e", "is_human": true, "px": 544.4, "py": 798.4, "t": 0.4, "event": "Position"}, {"user_id": "484d027b-069e-4b38-b99a-54f3bbfedc7e", "is_human": true, "px": 536.6, "py": 805.4, "t": 0.4, "event": "Position"}, {"user_id": "484d027b-069e-4b38-b99a-54f3bbfedc7e", "is_human": true, "px": 529.9, "py": 794.7, "t": 0.5, "event": "Position"}, {"user_id": "484d027b-069e-4b38-b99a-54f3bbfedc7e", "is_human": true, "px": 524.8, "py": 794.3, "t": 0.5, "event": "Position"}, {"user_id": "484d027b-069e-4b38-b99a-54f3bbfedc7e", "is_human": true, "px": 534.0, "py": 799.3, "t": 0.5, "event": "Position"}, {"user_id": "484d027b-069e-4b38-b99a-54f3bbfedc7e", "is_human": true, "px": 540.0, "py": 792.0, "t": 0.5, "event": "Position"}, {"user_id": "484d027b-069e-4b38-b99a-54f3bbfedc7e", "is_human": true, "px": 547.4, "py": 777.3, "t": 0.5, "event": "Position"}, {"user_id": "484d027b-069e-4b38-b99a-54f3bbfedc7e", "is_human": true, "px": 546.0, "py": 775.7, "t": 0.5, "event": "Position"}, {"user_id": "484d027b-069e-4b38-b99a-54f3bbfedc7e", "is_human": true, "px": 542.8, "py": 778.0, "t": 0.5, "event": "Position"}, {"user_id": "484d027b-069e-4b38-b99a-54f3bbfedc7e", "is_human": true, "px": 548.7, "py": 782.6, "t": 0.5, "event": "Position"}, {"user_id": "484d027b-069e-4b38-b99a-54f3bbfedc7e", "is_human": true, "px": 557.8, "py": 791.0, "t": 0.5, "event": "Position"}, {"user_id": "484d027b-069e-4b38-b99a-54f3bbfedc7e", "is_human": true, "px": 562.7, "py": 796.8, "t": 0.5, "event": "Position"}, {"user_id": "484d027b-069e-4b38-b99a-54f3bbfedc7e", "is_human": true, "px": 564.2, "py": 797.4, "t": 0.5, "event": "Position"}, {"user_id": "484d027b-069e-4b38-b99a-54f3bbfedc7e", "is_human": true, "px": 561.1, "py": 814.6, "t": 0.5, "event": "Position"}, {"user_id": "484d027b-069e-4b38-b99a-54f3bbfedc7e", "is_human": true, "px": 564.0, "py": 814.4, "t": 0.5, "event": "Position"}, {"user_id": "484d027b-069e-4b38-b99a-54f3bbfedc7e", "is_human": true, "px": 579.3, "py": 823.9, "t": 0.6, "event": "Position"}, {"user_id": "484d027b-069e-4b38-b99a-54f3bbfedc7e", "is_human": true, "px": 605.6, "py": 813.3, "t": 0.6, "event": "Position"}, {"user_id": "484d027b-069e-4b38-b99a-54f3bbfedc7e", "is_human": true, "px": 609.0, "py": 813.9, "t": 0.6, "event": "Position"}, {"user_id": "484d027b-069e-4b38-b99a-54f3bbfedc7e", "is_human": true, "px": 609.7, "py": 821.9, "t": 0.6, "event": "Position"}, {"user_id": "484d027b-069e-4b38-b99a-54f3bbfedc7e", "is_human": true, "px": 613.1, "py": 817.2, "t": 0.6, "event": "Position"}, {"user_id": "484d027b-069e-4b38-b99a-54f3bbfedc7e", "is_human": true, "px": 618.3, "py": 815.5, "t": 0.6, "event": "Position"}, {"user_id": "484d027b-069e-4b38-b99a-54f3bbfedc7e", "is_human": true, "px": 622.7, "py": 813.6, "t": 0.6, "event": "Position"}, {"user_id": "484d027b-069e-4b38-b99a-54f3bbfedc7e", "is_human": true, "px": 623.9, "py": 820.2, "t": 0.6, "event": "Position"}, {"user_id": "484d027b-069e-4b38-b99a-54f3bbfedc7e", "is_human": true, "px": 613.1, "py": 824.7, "t": 0.6, "event": "Position"}, {"user_id": "484d027b-069e-4b38-b99a-54f3bbfedc7e", "is_human": true, "px": 607.9, "py": 813.7, "t": 0.6, "event": "Position"}, {"user_id": "484d027b-069e-4b38-b99a-54f3bbfedc7e", "is_human": true, "px": 597.6, "py": 827.4, "t": 0.6, "event": "Position"}, {"user_id": "484d027b-069e-4b38-b99a-54f3bbfedc7e", "is_human": true, "px": 591.3, "py": 837.3, "t": 0.7, "event": "Position"}, {"user_id": "484d027b-069e-4b38-b99a-54f3bbfedc7e", "is_human": true, "px": 594.5, "py": 862.1, "t": 0.7, "event": "Position"}, {"user_id": "484d027b-069e-4b38-b99a-54f3bbfedc7e", "is_human": true, "px": 578.0, "py": 873.3, "t": 0.7, "event": "Position"}, {"user_id": "484d027b-069e-4b38-b99a-54f3bbfedc7e", "is_human": true, "px": 578.1, "py": 870.2, "t": 0.7, "event": "Position"}, {"user_id": "484d027b-069e-4b38-b99a-54f3bbfedc7e", "is_human": true, "px": 578.2, "py": 875.2, "t": 0.7, "event": "Position"}, {"user_id": "484d027b-069e-4b38-b99a-54f3bbfedc7e", "is_human": true, "px": 576.0, "py": 866.9, "t": 0.7, "event": "Position"}, {"user_id": "484d027b-069e-4b38-b99a-54f3bbfedc7e", "is_human": true, "px": 579.4, "py": 869.8, "t": 0.7, "event": "Position"}, {"user_id": "484d027b-069e-4b38-b99a-54f3bbfedc7e", "is_human": true, "px": 579.6, "py": 874.3, "t": 0.7, "event": "Position"}, {"user_id": "484d027b-069e-4b38-b99a-54f3bbfedc7e", "is_human": true, "px": 588.6, "py": 883.5, "t": 0.7, "event": "Position"}, {"user_id": "484d027b-069e-4b38-b99a-54f3bbfedc7e", "is_human": true, "px": 586.3, "py": 872.2, "t": 0.7, "event": "Position"}, {"user_id": "484d027b-069e-4b38-b99a-54f3bbfedc7e", "is_human": true, "px": 589.8, "py": 848.4, "t": 0.7, "event": "Position"}, {"user_id": "484d027b-069e-4b38-b99a-54f3bbfedc7e", "is_human": true, "px": 591.5, "py": 850.5, "t": 0.7, "event": "Position"}, {"user_id": "484d027b-069e-4b38-b99a-54f3bbfedc7e", "is_human": true, "px": 588.6, "py": 843.6, "t": 0.7, "event": "Position"}, {"user_id": "484d027b-069e-4b38-b99a-54f3bbfedc7e", "is_human": true, "px": 605.8, "py": 847.0, "t": 0.7, "event": "Position"}, {"user_id": "484d027b-069e-4b38-b99a-54f3bbfedc7e", "is_human": true, "px": 589.4, "py": 815.0, "t": 0.7, "event": "Position"}, {"user_id": "484d027b-069e-4b38-b99a-54f3bbfedc7e", "is_human": true, "px": 583.4, "py": 792.7, "t": 0.7, "event": "Position"}, {"user_id": "484d027b-069e-4b38-b99a-54f3bbfedc7e", "is_human": true, "px": 587.0, "py": 763.8, "t": 0.7, "event": "Position"}, {"user_id": "484d027b-069e-4b38-b99a-54f3bbfedc7e", "is_human": true, "px": 568.5, "py": 733.7, "t": 0.8, "event": "Position"}, {"user_id": "484d027b-069e-4b38-b99a-54f3bbfedc7e", "is_human": true, "px": 564.8, "py": 700.0, "t": 0.8, "event": "Position"}, {"user_id": "484d027b-069e-4b38-b99a-54f3bbfedc7e", "is_human": true, "px": 566.6, "py": 705.7, "t": 0.8, "event": "Position"}, {"user_id": "484d027b-069e-4b38-b99a-54f3bbfedc7e", "is_human": true, "px": 568.4, "py": 741.3, "t": 0.8, "event": "Position"}, {"user_id": "484d027b-069e-4b38-b99a-54f3bbfedc7e", "is_human": true, "px": 570.0, "py": 751.9, "t": 0.8, "event": "Position"}, {"user_id": "484d027b-069e-4b38-b99a-54f3bbfedc7e", "is_human": true, "px": 583.8, "py": 769.3, "t": 0.8, "event": "Position"}, {"user_id": "484d027b-069e-4b38-b99a-54f3bbfedc7e", "is_human": true, "px": 567.7, "py": 799.4, "t": 0.8, "event": "Position"}, {"user_id": "484d027b-069e-4b38-b99a-54f3bbfedc7e", "is_human": true, "px": 544.0, "py": 819.1, "t": 0.8, "event": "Position"}, {"user_id": "484d027b-069e-4b38-b99a-54f3bbfedc7e", "is_human": true, "px": 524.3, "py": 811.2, "t": 0.8, "event": "Position"}, {"user_id": "484d027b-069e-4b38-b99a-54f3bbfedc7e", "is_human": true, "px": 504.7, "py": 830.9, "t": 0.8, "event": "Position"}], "combat": [{"user_id": "484d027b-069e-4b38-b99a-54f3bbfedc7e", "is_human": true, "px": 360.5, "py": 893.9, "t": 0.1, "event": "Loot"}, {"user_id": "484d027b-069e-4b38-b99a-54f3bbfedc7e", "is_human": true, "px": 360.9, "py": 892.6, "t": 0.1, "event": "Loot"}, {"user_id": "484d027b-069e-4b38-b99a-54f3bbfedc7e", "is_human": true, "px": 359.1, "py": 889.2, "t": 0.1, "event": "Loot"}, {"user_id": "484d027b-069e-4b38-b99a-54f3bbfedc7e", "is_human": true, "px": 354.8, "py": 883.3, "t": 0.1, "event": "Loot"}, {"user_id": "484d027b-069e-4b38-b99a-54f3bbfedc7e", "is_human": true, "px": 354.8, "py": 883.3, "t": 0.1, "event": "Loot"}, {"user_id": "484d027b-069e-4b38-b99a-54f3bbfedc7e", "is_human": true, "px": 372.2, "py": 895.1, "t": 0.1, "event": "Loot"}, {"user_id": "484d027b-069e-4b38-b99a-54f3bbfedc7e", "is_human": true, "px": 373.9, "py": 894.6, "t": 0.1, "event": "Loot"}, {"user_id": "484d027b-069e-4b38-b99a-54f3bbfedc7e", "is_human": true, "px": 371.7, "py": 889.3, "t": 0.1, "event": "Loot"}, {"user_id": "484d027b-069e-4b38-b99a-54f3bbfedc7e", "is_human": true, "px": 371.7, "py": 889.3, "t": 0.1, "event": "Loot"}, {"user_id": "484d027b-069e-4b38-b99a-54f3bbfedc7e", "is_human": true, "px": 417.9, "py": 806.9, "t": 0.2, "event": "Loot"}, {"user_id": "484d027b-069e-4b38-b99a-54f3bbfedc7e", "is_human": true, "px": 420.2, "py": 801.3, "t": 0.2, "event": "Loot"}, {"user_id": "484d027b-069e-4b38-b99a-54f3bbfedc7e", "is_human": true, "px": 408.2, "py": 797.5, "t": 0.2, "event": "Loot"}, {"user_id": "484d027b-069e-4b38-b99a-54f3bbfedc7e", "is_human": true, "px": 401.1, "py": 806.0, "t": 0.2, "event": "Loot"}, {"user_id": "484d027b-069e-4b38-b99a-54f3bbfedc7e", "is_human": true, "px": 405.0, "py": 801.9, "t": 0.2, "event": "Loot"}, {"user_id": "484d027b-069e-4b38-b99a-54f3bbfedc7e", "is_human": true, "px": 406.2, "py": 805.2, "t": 0.2, "event": "Loot"}, {"user_id": "484d027b-069e-4b38-b99a-54f3bbfedc7e", "is_human": true, "px": 412.7, "py": 799.5, "t": 0.3, "event": "Loot"}, {"user_id": "484d027b-069e-4b38-b99a-54f3bbfedc7e", "is_human": true, "px": 534.7, "py": 763.6, "t": 0.3, "event": "BotKill"}, {"user_id": "484d027b-069e-4b38-b99a-54f3bbfedc7e", "is_human": true, "px": 548.0, "py": 769.2, "t": 0.3, "event": "Loot"}, {"user_id": "484d027b-069e-4b38-b99a-54f3bbfedc7e", "is_human": true, "px": 548.0, "py": 769.2, "t": 0.3, "event": "Loot"}, {"user_id": "484d027b-069e-4b38-b99a-54f3bbfedc7e", "is_human": true, "px": 532.8, "py": 785.1, "t": 0.4, "event": "BotKill"}, {"user_id": "484d027b-069e-4b38-b99a-54f3bbfedc7e", "is_human": true, "px": 534.5, "py": 782.7, "t": 0.4, "event": "Loot"}, {"user_id": "484d027b-069e-4b38-b99a-54f3bbfedc7e", "is_human": true, "px": 534.5, "py": 782.7, "t": 0.4, "event": "Loot"}, {"user_id": "484d027b-069e-4b38-b99a-54f3bbfedc7e", "is_human": true, "px": 551.3, "py": 794.1, "t": 0.4, "event": "Loot"}, {"user_id": "484d027b-069e-4b38-b99a-54f3bbfedc7e", "is_human": true, "px": 556.5, "py": 810.2, "t": 0.4, "event": "Loot"}, {"user_id": "484d027b-069e-4b38-b99a-54f3bbfedc7e", "is_human": true, "px": 529.9, "py": 794.7, "t": 0.5, "event": "Loot"}, {"user_id": "484d027b-069e-4b38-b99a-54f3bbfedc7e", "is_human": true, "px": 526.3, "py": 795.9, "t": 0.5, "event": "Loot"}, {"user_id": "484d027b-069e-4b38-b99a-54f3bbfedc7e", "is_human": true, "px": 546.8, "py": 777.0, "t": 0.5, "event": "Loot"}, {"user_id": "484d027b-069e-4b38-b99a-54f3bbfedc7e", "is_human": true, "px": 564.0, "py": 814.4, "t": 0.6, "event": "Loot"}, {"user_id": "484d027b-069e-4b38-b99a-54f3bbfedc7e", "is_human": true, "px": 609.0, "py": 813.9, "t": 0.6, "event": "Loot"}, {"user_id": "484d027b-069e-4b38-b99a-54f3bbfedc7e", "is_human": true, "px": 607.7, "py": 814.3, "t": 0.6, "event": "Loot"}, {"user_id": "484d027b-069e-4b38-b99a-54f3bbfedc7e", "is_human": true, "px": 607.8, "py": 813.2, "t": 0.6, "event": "Loot"}, {"user_id": "484d027b-069e-4b38-b99a-54f3bbfedc7e", "is_human": true, "px": 578.5, "py": 871.6, "t": 0.7, "event": "Loot"}, {"user_id": "484d027b-069e-4b38-b99a-54f3bbfedc7e", "is_human": true, "px": 591.5, "py": 850.5, "t": 0.7, "event": "Loot"}]}