{"match_id": "3febfe9a-d86a-4a7b-8388-c0666b670ac7.nakama-0", "map_id": "AmbroseValley", "positions": [{"user_id": "ff436bfe-1b54-4098-a248-4bfbe123f3f1", "is_human": true, "px": 227.0, "py": 100.3, "t": 0.0, "event": "Position"}, {"user_id": "ff436bfe-1b54-4098-a248-4bfbe123f3f1", "is_human": true, "px": 230.1, "py": 105.4, "t": 0.1, "event": "Position"}, {"user_id": "ff436bfe-1b54-4098-a248-4bfbe123f3f1", "is_human": true, "px": 228.1, "py": 120.7, "t": 0.1, "event": "Position"}, {"user_id": "ff436bfe-1b54-4098-a248-4bfbe123f3f1", "is_human": true, "px": 221.5, "py": 129.8, "t": 0.1, "event": "Position"}, {"user_id": "ff436bfe-1b54-4098-a248-4bfbe123f3f1", "is_human": true, "px": 228.8, "py": 131.1, "t": 0.1, "event": "Position"}, {"user_id": "ff436bfe-1b54-4098-a248-4bfbe123f3f1", "is_human": true, "px": 232.8, "py": 142.1, "t": 0.1, "event": "Position"}, {"user_id": "ff436bfe-1b54-4098-a248-4bfbe123f3f1", "is_human": true, "px": 246.4, "py": 141.2, "t": 0.1, "event": "Position"}, {"user_id": "ff436bfe-1b54-4098-a248-4bfbe123f3f1", "is_human": true, "px": 250.1, "py": 138.6, "t": 0.1, "event": "Position"}, {"user_id": "ff436bfe-1b54-4098-a248-4bfbe123f3f1", "is_human": true, "px": 260.3, "py": 150.8, "t": 0.1, "event": "Position"}, {"user_id": "ff436bfe-1b54-4098-a248-4bfbe123f3f1", "is_human": true, "px": 262.9, "py": 168.1, "t": 0.1, "event": "Position"}, {"user_id": "ff436bfe-1b54-4098-a248-4bfbe123f3f1", "is_human": true, "px": 265.9, "py": 179.1, "t": 0.1, "event": "Position"}, {"user_id": "ff436bfe-1b54-4098-a248-4bfbe123f3f1", "is_human": true, "px": 274.0, "py": 190.4, "t": 0.1, "event": "Position"}, {"user_id": "ff436bfe-1b54-4098-a248-4bfbe123f3f1", "is_human": true, "px": 265.7, "py": 171.4, "t": 0.1, "event": "Position"}, {"user_id": "ff436bfe-1b54-4098-a248-4bfbe123f3f1", "is_human": true, "px": 279.0, "py": 199.5, "t": 0.1, "event": "Position"}, {"user_id": "ff436bfe-1b54-4098-a248-4bfbe123f3f1", "is_human": true, "px": 278.4, "py": 202.6, "t": 0.1, "event": "Position"}, {"user_id": "ff436bfe-1b54-4098-a248-4bfbe123f3f1", "is_human": true, "px": 283.6, "py": 202.7, "t": 0.2, "event": "Position"}, {"user_id": "ff436bfe-1b54-4098-a248-4bfbe123f3f1", "is_human": true, "px": 284.5, "py": 218.4, "t": 0.2, "event": "Position"}, {"user_id": "ff436bfe-1b54-4098-a248-4bfbe123f3f1", "is_human": true, "px": 287.4, "py": 236.4, "t": 0.2, "event": "Position"}, {"user_id": "ff436bfe-1b54-4098-a248-4bfbe123f3f1", "is_human": true, "px": 271.9, "py": 266.1, "t": 0.2, "event": "Position"}, {"user_id": "ff436bfe-1b54-4098-a248-4bfbe123f3f1", "is_human": true, "px": 267.2, "py": 277.6, "t": 0.2, "event": "Position"}, {"user_id": "ff436bfe-1b54-4098-a248-4bfbe123f3f1", "is_human": true, "px": 265.2, "py": 284.7, "t": 0.2, "event": "Position"}, {"user_id": "ff436bfe-1b54-4098-a248-4bfbe123f3f1", "is_human": true, "px": 271.6, "py": 279.3, "t": 0.2, "event": "Position"}, {"user_id": "ff436bfe-1b54-4098-a248-4bfbe123f3f1", "is_human": true, "px": 260.0, "py": 286.5, "t": 0.2, "event": "Position"}, {"user_id": "ff436bfe-1b54-4098-a248-4bfbe123f3f1", "is_human": true, "px": 247.2, "py": 289.8, "t": 0.2, "event": "Position"}, {"user_id": "ff436bfe-1b54-4098-a248-4bfbe123f3f1", "is_human": true, "px": 223.7, "py": 307.3, "t": 0.2, "event": "Position"}, {"user_id": "ff436bfe-1b54-4098-a248-4bfbe123f3f1", "is_human": true, "px": 206.3, "py": 323.7, "t": 0.2, "event": "Position"}, {"user_id": "ff436bfe-1b54-4098-a248-4bfbe123f3f1", "is_human": true, "px": 187.9, "py": 343.7, "t": 0.2, "event": "Position"}, {"user_id": "ff436bfe-1b54-4098-a248-4bfbe123f3f1", "is_human": true, "px": 168.4, "py": 365.3, "t": 0.2, "event": "Position"}, {"user_id": "ff436bfe-1b54-4098-a248-4bfbe123f3f1", "is_human": true, "px": 160.2, "py": 380.0, "t": 0.2, "event": "Position"}, {"user_id": "ff436bfe-1b54-4098-a248-4bfbe123f3f1", "is_human": true, "px": 170.6, "py": 391.8, "t": 0.2, "event": "Position"}, {"user_id": "ff436bfe-1b54-4098-a248-4bfbe123f3f1", "is_human": true, "px": 168.6, "py": 399.9, "t": 0.2, "event": "Position"}, {"user_id": "ff436bfe-1b54-4098-a248-4bfbe123f3f1", "is_human": true, "px": 167.0, "py": 404.7, "t": 0.2, "event": "Position"}, {"user_id": "ff436bfe-1b54-4098-a248-4bfbe123f3f1", "is_human": true, "px": 160.5, "py": 406.2, "t": 0.2, "event": "Position"}, {"user_id": "ff436bfe-1b54-4098-a248-4bfbe123f3f1", "is_human": true, "px": 152.2, "py": 404.7, "t": 0.3, "event": "Position"}, {"user_id": "ff436bfe-1b54-4098-a248-4bfbe123f3f1", "is_human": true, "px": 148.8, "py": 396.9, "t": 0.3, "event": "Position"}, {"user_id": "ff436bfe-1b54-4098-a248-4bfbe123f3f1", "is_human": true, "px": 134.8, "py": 395.7, "t": 0.3, "event": "Position"}, {"user_id": "ff436bfe-1b54-4098-a248-4bfbe123f3f1", "is_human": true, "px": 121.1, "py": 401.9, "t": 0.3, "event": "Position"}, {"user_id": "ff436bfe-1b54-4098-a248-4bfbe123f3f1", "is_human": true, "px": 109.2, "py": 412.1, "t": 0.3, "event": "Position"}, {"user_id": "ff436bfe-1b54-4098-a248-4bfbe123f3f1", "is_human": true, "px": 102.8, "py": 411.5, "t": 0.3, "event": "Position"}, {"user_id": "ff436bfe-1b54-4098-a248-4bfbe123f3f1", "is_human": true, "px": 90.0, "py": 408.5, "t": 0.3, "event": "Position"}, {"user_id": "ff436bfe-1b54-4098-a248-4bfbe123f3f1", "is_human": true, "px": 104.5, "py": 409.1, "t": 0.3, "event": "Position"}, {"user_id": "ff436bfe-1b54-4098-a248-4bfbe123f3f1", "is_human": true, "px": 103.1, "py": 412.2, "t": 0.3, "event": "Position"}, {"user_id": "ff436bfe-1b54-4098-a248-4bfbe123f3f1", "is_human": true, "px": 111.2, "py": 400.2, "t": 0.3, "event": "Position"}, {"user_id": "ff436bfe-1b54-4098-a248-4bfbe123f3f1", "is_human": true, "px": 95.7, "py": 398.7, "t": 0.3, "event": "Position"}, {"user_id": "ff436bfe-1b54-4098-a248-4bfbe123f3f1", "is_human": true, "px": 105.3, "py": 393.0, "t": 0.3, "event": "Position"}, {"user_id": "ff436bfe-1b54-4098-a248-4bfbe123f3f1", "is_human": true, "px": 136.2, "py": 409.1, "t": 0.3, "event": "Position"}, {"user_id": "ff436bfe-1b54-4098-a248-4bfbe123f3f1", "is_human": true, "px": 169.4, "py": 411.3, "t": 0.3, "event": "Position"}, {"user_id": "ff436bfe-1b54-4098-a248-4bfbe123f3f1", "is_human": true, "px": 201.6, "py": 421.5, "t": 0.3, "event": "Position"}, {"user_id": "ff436bfe-1b54-4098-a248-4bfbe123f3f1", "is_human": true, "px": 223.1, "py": 428.5, "t": 0.3, "event": "Position"}, {"user_id": "ff436bfe-1b54-4098-a248-4bfbe123f3f1", "is_human": true, "px": 252.4, "py": 444.6, "t": 0.3, "event": "Position"}, {"user_id": "ff436bfe-1b54-4098-a248-4bfbe123f3f1", "is_human": true, "px": 268.3, "py": 464.5, "t": 0.3, "event": "Position"}, {"user_id": "ff436bfe-1b54-4098-a248-4bfbe123f3f1", "is_human": true, "px": 293.3, "py": 472.2, "t": 0.3, "event": "Position"}, {"user_id": "ff436bfe-1b54-4098-a248-4bfbe123f3f1", "is_human": true, "px": 325.8, "py": 471.5, "t": 0.4, "event": "Position"}, {"user_id": "ff436bfe-1b54-4098-a248-4bfbe123f3f1", "is_human": true, "px": 348.1, "py": 478.6, "t": 0.4, "event": "Position"}, {"user_id": "ff436bfe-1b54-4098-a248-4bfbe123f3f1", "is_human": true, "px": 354.9, "py": 509.2, "t": 0.4, "event": "Position"}, {"user_id": "ff436bfe-1b54-4098-a248-4bfbe123f3f1", "is_human": true, "px": 365.0, "py": 530.4, "t": 0.4, "event": "Position"}, {"user_id": "ff436bfe-1b54-4098-a248-4bfbe123f3f1", "is_human": true, "px": 383.3, "py": 545.5, "t": 0.4, "event": "Position"}, {"user_id": "ff436bfe-1b54-4098-a248-4bfbe123f3f1", "is_human": true, "px": 394.1, "py": 523.2, "t": 0.4, "event": "Position"}, {"user_id": "ff436bfe-1b54-4098-a248-4bfbe123f3f1", "is_human": true, "px": 393.7, "py": 526.7, "t": 0.4, "event": "Position"}, {"user_id": "ff436bfe-1b54-4098-a248-4bfbe123f3f1", "is_human": true, "px": 392.4, "py": 525.8, "t": 0.4, "event": "Position"}, {"user_id": "ff436bfe-1b54-4098-a248-4bfbe123f3f1", "is_human": true, "px": 393.3, "py": 520.3, "t": 0.4, "event": "Position"}, {"user_id": "ff436bfe-1b54-4098-a248-4bfbe123f3f1", "is_human": true, "px": 406.9, "py": 489.7, "t": 0.4, "event": "Position"}, {"user_id": "ff436bfe-1b54-4098-a248-4bfbe123f3f1", "is_human": true, "px": 440.0, "py": 492.4, "t": 0.4, "event": "Position"}, {"user_id": "ff436bfe-1b54-4098-a248-4bfbe123f3f1", "is_human": true, "px": 469.6, "py": 509.3, "t": 0.4, "event": "Position"}, {"user_id": "ff436bfe-1b54-4098-a248-4bfbe123f3f1", "is_human": true, "px": 490.4, "py": 527.4, "t": 0.4, "event": "Position"}, {"user_id": "ff436bfe-1b54-4098-a248-4bfbe123f3f1", "is_human": true, "px": 512.5, "py": 547.1, "t": 0.4, "event": "Position"}, {"user_id": "ff436bfe-1b54-4098-a248-4bfbe123f3f1", "is_human": true, "px": 515.3, "py": 573.7, "t": 0.4, "event": "Position"}], "combat": [{"user_id": "ff436bfe-1b54-4098-a248-4bfbe123f3f1", "is_human": true, "px": 221.5, "py": 129.8, "t": 0.1, "event": "Loot"}, {"user_id": "ff436bfe-1b54-4098-a248-4bfbe123f3f1", "is_human": true, "px": 246.4, "py": 141.2, "t": 0.1, "event": "Loot"}, {"user_id": "ff436bfe-1b54-4098-a248-4bfbe123f3f1", "is_human": true, "px": 246.4, "py": 141.2, "t": 0.1, "event": "Loot"}, {"user_id": "ff436bfe-1b54-4098-a248-4bfbe123f3f1", "is_human": true, "px": 278.3, "py": 202.7, "t": 0.1, "event": "Loot"}, {"user_id": "ff436bfe-1b54-4098-a248-4bfbe123f3f1", "is_human": true, "px": 266.8, "py": 278.3, "t": 0.2, "event": "Loot"}, {"user_id": "ff436bfe-1b54-4098-a248-4bfbe123f3f1", "is_human": true, "px": 149.7, "py": 396.7, "t": 0.3, "event": "Loot"}, {"user_id": "ff436bfe-1b54-4098-a248-4bfbe123f3f1", "is_human": true, "px": 89.8, "py": 408.5, "t": 0.3, "event": "Loot"}, {"user_id": "ff436bfe-1b54-4098-a248-4bfbe123f3f1", "is_human": true, "px": 89.8, "py": 408.5, "t": 0.3, "event": "Loot"}, {"user_id": "ff436bfe-1b54-4098-a248-4bfbe123f3f1", "is_human": true, "px": 104.5, "py": 409.1, "t": 0.3, "event": "Loot"}, {"user_id": "ff436bfe-1b54-4098-a248-4bfbe123f3f1", "is_human": true, "px": 95.7, "py": 398.7, "t": 0.3, "event": "Loot"}, {"user_id": "ff436bfe-1b54-4098-a248-4bfbe123f3f1", "is_human": true, "px": 515.4, "py": 573.5, "t": 0.4, "event": "BotKilled"}]}